html_content/__init__.py
html_content/default.py
html_content/html_content.py
html_content/type.py
html_content-0.0.2.dist-info/LICENSE
html_content-0.0.2.dist-info/METADATA
html_content-0.0.2.dist-info/WHEEL
html_content-0.0.2.dist-info/top_level.txt
html_content-0.0.2.dist-info/RECORD
